data_mapper/__init__.py
data_mapper/errors.py
data_mapper/result.py
data_mapper/shortcuts.py
data_mapper/utils.py
data_mapper/mappers/__init__.py
data_mapper/mappers/mapper.py
data_mapper/mappers/object.py
data_mapper/properties/__init__.py
data_mapper/properties/abstract.py
data_mapper/properties/boolean.py
data_mapper/properties/compound.py
data_mapper/properties/compound_list.py
data_mapper/properties/dict.py
data_mapper/properties/float.py
data_mapper/properties/integer.py
data_mapper/properties/list.py
data_mapper/properties/operations.py
data_mapper/properties/property.py
data_mapper/properties/ref.py
data_mapper/properties/string.py
data_mapper/properties/value.py
data_mapper/properties/functional/__init__.py
data_mapper/properties/functional/binary_operation.py
data_mapper/properties/functional/function.py
data_mapper/properties/functional/operation.py
data_mapper/properties/functional/operators.py
data_mapper/properties/functional/ternary_operation.py
data_mapper/properties/functional/unary_operation.py
data_mapper/tests/__init__.py
data_mapper/tests/boolean_property.py
data_mapper/tests/compound_list_property.py
data_mapper/tests/compound_property.py
data_mapper/tests/dict_property.py
data_mapper/tests/examples.py
data_mapper/tests/float_property.py
data_mapper/tests/function.py
data_mapper/tests/integer_property.py
data_mapper/tests/list_property.py
data_mapper/tests/mapper.py
data_mapper/tests/object.py
data_mapper/tests/operation.py
data_mapper/tests/operators.py
data_mapper/tests/property.py
data_mapper/tests/property_ref.py
data_mapper/tests/result.py
data_mapper/tests/shortcuts.py
data_mapper/tests/string_property.py
data_mapper/tests/test_utils.py
data_mapper/tests/value.py
data_mapper-4.4.1.dist-info/LICENSE
data_mapper-4.4.1.dist-info/METADATA
data_mapper-4.4.1.dist-info/WHEEL
data_mapper-4.4.1.dist-info/top_level.txt
data_mapper-4.4.1.dist-info/RECORD
