Metadata-Version: 2.1
Name: data-mapper
Version: 4.4.1
Summary: A declarative data mapper
Home-page: https://github.com/OkThought/data-mapper
Author: OkThought
Author-email: bogush.vano@gmail.com
License: UNKNOWN
Platform: UNKNOWN
Classifier: Programming Language :: Python :: 3
Classifier: License :: OSI Approved :: MIT License
Classifier: Operating System :: OS Independent
